README.md
setup.py
Dora/__init__.py
Dora/main.py
Dora/spec.py
Dora.egg-info/PKG-INFO
Dora.egg-info/SOURCES.txt
Dora.egg-info/dependency_links.txt
Dora.egg-info/requires.txt
Dora.egg-info/top_level.txt