Metadata-Version: 1.0
Name: Dora
Version: 0.0.3
Summary: Exploratory data analysis toolkit for Python
Home-page: UNKNOWN
Author: Nathan Epstein
Author-email: ne2210@columbia.edu
License: MIT
Keywords: exploratory data analysis
Platform: UNKNOWN
